slide_extractor/__init__.py
slide_extractor/__main__.py
slide_extractor/main.py
slide_extractor-1.0.6.dist-info/LICENSE
slide_extractor-1.0.6.dist-info/METADATA
slide_extractor-1.0.6.dist-info/WHEEL
slide_extractor-1.0.6.dist-info/entry_points.txt
slide_extractor-1.0.6.dist-info/top_level.txt
slide_extractor-1.0.6.dist-info/RECORD
