Metadata-Version: 2.1
Name: slide-extractor
Version: 1.0.6
Summary: A simple commandline app to extract slides from videos,lectures and presentations
Home-page: https://github.com/Slide-extractor-beta/slide-extractor
Download-URL: https://github.com/Slide-extractor-beta/slide-extractor/archive/refs/tags/v1.0.0-beta.tar.gz
Author: Vivek Anand, Ashish Manglani
Author-email: vivek17212797@gmail.com
License: MIT
Keywords: slide-extractor,slide_extractor,extractor,slide,slide extractor
Requires-Python: >=3.5
License-File: LICENSE
Requires-Dist: colorama
Requires-Dist: numpy
Requires-Dist: opencv-python
Requires-Dist: Pillow
Requires-Dist: tqdm
